{"fine_grained_deps": {}, "tree": {".class": "MypyFile", "_fullname": "collision", "_name": null, "is_stub": false, "names": {".class": "SymbolTable", "Box": {".class": "SymbolTableNode", "alias_tvars": [], "kind": "TypeAlias", "node": {".class": "Var", "flags": [], "fullname": "collision.Box", "name": "Box", "type": {".class": "CallableType", "arg_kinds": [0, 0], "arg_names": ["upper_left", "dimensions"], "arg_types": ["builtins.complex", {".class": "TupleType", "fallback": "sdl.Dimensions", "implicit": false, "items": ["builtins.int", "builtins.int"]}], "bound_args": [{".class": "TupleType", "fallback": {".class": "Instance", "args": ["builtins.object"], "type_ref": "builtins.tuple"}, "implicit": false, "items": ["builtins.complex", {".class": "TupleType", "fallback": "sdl.Dimensions", "implicit": false, "items": ["builtins.int", "builtins.int"]}]}], "fallback": "builtins.type", "implicit": false, "is_classmethod_class": false, "is_ellipsis_args": false, "name": null, "ret_type": {".class": "TupleType", "fallback": "sdl.Rectangle", "implicit": false, "items": ["builtins.complex", {".class": "TupleType", "fallback": "sdl.Dimensions", "implicit": false, "items": ["builtins.int", "builtins.int"]}]}, "variables": []}}, "type_override": {".class": "TupleType", "fallback": "sdl.Rectangle", "implicit": false, "items": ["builtins.complex", {".class": "TupleType", "fallback": "sdl.Dimensions", "implicit": false, "items": ["builtins.int", "builtins.int"]}]}}, "Boxes": {".class": "SymbolTableNode", "alias_tvars": [], "kind": "TypeAlias", "node": {".class": "Var", "flags": [], "fullname": "collision.Boxes", "name": "Boxes", "type": {".class": "CallableType", "arg_kinds": [], "arg_names": [], "arg_types": [], "bound_args": [null], "fallback": "builtins.type", "implicit": false, "is_classmethod_class": false, "is_ellipsis_args": false, "name": null, "ret_type": {".class": "Instance", "args": [{".class": "TupleType", "fallback": "sdl.Rectangle", "implicit": false, "items": ["builtins.complex", {".class": "TupleType", "fallback": "sdl.Dimensions", "implicit": false, "items": ["builtins.int", "builtins.int"]}]}], "type_ref": "typing.Iterable"}, "variables": []}}, "type_override": {".class": "Instance", "args": [{".class": "TupleType", "fallback": "sdl.Rectangle", "implicit": false, "items": ["builtins.complex", {".class": "TupleType", "fallback": "sdl.Dimensions", "implicit": false, "items": ["builtins.int", "builtins.int"]}]}], "type_ref": "typing.Iterable"}}, "Iterable": {".class": "SymbolTableNode", "cross_ref": "typing.Iterable", "kind": "Gdef"}, "Wall": {".class": "SymbolTableNode", "alias_tvars": [], "kind": "TypeAlias", "node": {".class": "Var", "flags": [], "fullname": "collision.Wall", "name": "Wall", "type": {".class": "CallableType", "arg_kinds": [0, 0], "arg_names": ["position", "free_vector"], "arg_types": ["builtins.complex", "builtins.complex"], "bound_args": [{".class": "TupleType", "fallback": {".class": "Instance", "args": ["builtins.complex"], "type_ref": "builtins.tuple"}, "implicit": false, "items": ["builtins.complex", "builtins.complex"]}], "fallback": "builtins.type", "implicit": false, "is_classmethod_class": false, "is_ellipsis_args": false, "name": null, "ret_type": {".class": "TupleType", "fallback": "utils.BoundVector", "implicit": false, "items": ["builtins.complex", "builtins.complex"]}, "variables": []}}, "type_override": {".class": "TupleType", "fallback": "utils.BoundVector", "implicit": false, "items": ["builtins.complex", "builtins.complex"]}}, "Walls": {".class": "SymbolTableNode", "alias_tvars": [], "kind": "TypeAlias", "node": {".class": "Var", "flags": [], "fullname": "collision.Walls", "name": "Walls", "type": {".class": "CallableType", "arg_kinds": [], "arg_names": [], "arg_types": [], "bound_args": [null], "fallback": "builtins.type", "implicit": false, "is_classmethod_class": false, "is_ellipsis_args": false, "name": null, "ret_type": {".class": "Instance", "args": [{".class": "TupleType", "fallback": "utils.BoundVector", "implicit": false, "items": ["builtins.complex", "builtins.complex"]}], "type_ref": "typing.Iterable"}, "variables": []}}, "type_override": {".class": "Instance", "args": [{".class": "TupleType", "fallback": "utils.BoundVector", "implicit": false, "items": ["builtins.complex", "builtins.complex"]}], "type_ref": "typing.Iterable"}}, "__doc__": {".class": "SymbolTableNode", "kind": "Gdef", "node": {".class": "Var", "flags": [], "fullname": "collision.__doc__", "name": "__doc__", "type": "builtins.str"}}, "__file__": {".class": "SymbolTableNode", "kind": "Gdef", "node": {".class": "Var", "flags": [], "fullname": "collision.__file__", "name": "__file__", "type": "builtins.str"}}, "__name__": {".class": "SymbolTableNode", "kind": "Gdef", "node": {".class": "Var", "flags": [], "fullname": "collision.__name__", "name": "__name__", "type": "builtins.str"}}, "__package__": {".class": "SymbolTableNode", "kind": "Gdef", "node": {".class": "Var", "flags": [], "fullname": "collision.__package__", "name": "__package__", "type": "builtins.str"}}, "sdl": {".class": "SymbolTableNode", "cross_ref": "sdl", "kind": "ModuleRef"}, "utils": {".class": "SymbolTableNode", "cross_ref": "utils", "kind": "ModuleRef"}}, "path": "/home/alexjones/projects/game/collision.py"}}
